Metadata-Version: 1.0
Name: fundamental-distrib
Version: 0.1
Summary: Gaussian and Binomial distributions
Home-page: UNKNOWN
Author: AWS Course
Author-email: UNKNOWN
License: UNKNOWN
Platform: UNKNOWN
